{"T": {"Predictor 2": {"Lower": 38.31, "Close": 39.01, "Upper": 39.71}, "Mean": {"Lower": 38.21, "Close": 39.2, "Upper": 40.21}, "Predictor 4": {"Lower": 38.91, "Close": 39.56, "Upper": 40.2}, "Predictor 1": {"Lower": 38.38, "Close": 39.16, "Upper": 39.93}, "Predictor 6": {"Lower": 36.84, "Close": 39.12, "Upper": 41.55}, "Predictor 3": {"Lower": 38.6, "Close": 39.31, "Upper": 40.03}, "Predictor 5": {"Lower": 38.21, "Close": 39.02, "Upper": 39.85}}, "INTC": {"Predictor 2": {"Lower": 34.66, "Close": 35.46, "Upper": 36.27}, "Mean": {"Lower": 34.39, "Close": 35.56, "Upper": 36.77}, "Predictor 4": {"Lower": 34.74, "Close": 35.5, "Upper": 36.25}, "Predictor 1": {"Lower": 34.93, "Close": 35.71, "Upper": 36.49}, "Predictor 6": {"Lower": 33.59, "Close": 35.85, "Upper": 38.27}, "Predictor 3": {"Lower": 34.4, "Close": 35.33, "Upper": 36.27}, "Predictor 5": {"Lower": 33.99, "Close": 35.49, "Upper": 37.05}}, "TSLA": {"Predictor 2": {"Lower": 323.09, "Close": 334.49, "Upper": 345.9}, "Mean": {"Lower": 313.88, "Close": 327.07, "Upper": 340.67}, "Predictor 4": {"Lower": 319.12, "Close": 328.47, "Upper": 337.83}, "Predictor 1": {"Lower": 314.48, "Close": 324.32, "Upper": 334.17}, "Predictor 6": {"Lower": 304.37, "Close": 323.89, "Upper": 344.65}, "Predictor 3": {"Lower": 317.58, "Close": 327.06, "Upper": 336.54}, "Predictor 5": {"Lower": 304.62, "Close": 324.16, "Upper": 344.95}}, "AMZN": {"Predictor 2": {"Lower": 922.74, "Close": 945.71, "Upper": 968.68}, "Mean": {"Lower": 966.07, "Close": 1009.28, "Upper": 1056.52}, "Predictor 4": {"Lower": 987.09, "Close": 1002.37, "Upper": 1017.65}, "Predictor 1": {"Lower": 970.0, "Close": 984.91, "Upper": 999.81}, "Predictor 6": {"Lower": 985.6, "Close": 1134.38, "Upper": 1305.61}, "Predictor 3": {"Lower": 981.89, "Close": 999.34, "Upper": 1016.79}, "Predictor 5": {"Lower": 949.1, "Close": 988.98, "Upper": 1030.54}}, "MSFT": {"Predictor 2": {"Lower": 72.36, "Close": 73.56, "Upper": 74.75}, "Mean": {"Lower": 70.66, "Close": 72.3, "Upper": 73.96}, "Predictor 4": {"Lower": 71.55, "Close": 72.66, "Upper": 73.76}, "Predictor 1": {"Lower": 72.02, "Close": 73.23, "Upper": 74.44}, "Predictor 6": {"Lower": 70.66, "Close": 72.78, "Upper": 74.97}, "Predictor 3": {"Lower": 67.05, "Close": 68.57, "Upper": 70.1}, "Predictor 5": {"Lower": 70.3, "Close": 72.97, "Upper": 75.74}}, "NVDA": {"Predictor 2": {"Lower": 152.62, "Close": 156.07, "Upper": 159.52}, "Mean": {"Lower": 156.81, "Close": 161.43, "Upper": 166.2}, "Predictor 4": {"Lower": 158.98, "Close": 161.52, "Upper": 164.06}, "Predictor 1": {"Lower": 163.45, "Close": 165.73, "Upper": 168.01}, "Predictor 6": {"Lower": 154.79, "Close": 162.9, "Upper": 171.43}, "Predictor 3": {"Lower": 158.88, "Close": 161.34, "Upper": 163.8}, "Predictor 5": {"Lower": 152.15, "Close": 161.01, "Upper": 170.38}}, "FB": {"Predictor 2": {"Lower": 137.01, "Close": 143.27, "Upper": 149.54}, "Mean": {"Lower": 158.87, "Close": 163.92, "Upper": 169.08}, "Predictor 4": {"Lower": 152.32, "Close": 155.38, "Upper": 158.45}, "Predictor 1": {"Lower": 171.36, "Close": 174.34, "Upper": 177.33}, "Predictor 6": {"Lower": 162.09, "Close": 169.53, "Upper": 177.31}, "Predictor 3": {"Lower": 168.52, "Close": 171.61, "Upper": 174.7}, "Predictor 5": {"Lower": 161.93, "Close": 169.36, "Upper": 177.12}}, "AAPL": {"Predictor 2": {"Lower": 146.45, "Close": 149.35, "Upper": 152.24}, "Mean": {"Lower": 144.9, "Close": 148.76, "Upper": 152.68}, "Predictor 4": {"Lower": 147.69, "Close": 150.38, "Upper": 153.08}, "Predictor 1": {"Lower": 142.07, "Close": 145.94, "Upper": 149.81}, "Predictor 6": {"Lower": 144.09, "Close": 148.86, "Upper": 153.78}, "Predictor 3": {"Lower": 144.55, "Close": 147.55, "Upper": 150.56}, "Predictor 5": {"Lower": 144.57, "Close": 150.46, "Upper": 156.59}}, "BAC": {"Predictor 2": {"Lower": 23.6, "Close": 24.31, "Upper": 25.03}, "Mean": {"Lower": 23.14, "Close": 24.04, "Upper": 24.97}, "Predictor 4": {"Lower": 23.35, "Close": 23.93, "Upper": 24.5}, "Predictor 1": {"Lower": 23.39, "Close": 24.05, "Upper": 24.71}, "Predictor 6": {"Lower": 22.62, "Close": 24.04, "Upper": 25.55}, "Predictor 3": {"Lower": 23.21, "Close": 23.87, "Upper": 24.52}, "Predictor 5": {"Lower": 22.64, "Close": 24.04, "Upper": 25.54}}, "BA": {"Predictor 2": {"Lower": 242.89, "Close": 246.65, "Upper": 250.42}, "Mean": {"Lower": 236.71, "Close": 241.56, "Upper": 246.51}, "Predictor 4": {"Lower": 240.43, "Close": 243.71, "Upper": 246.98}, "Predictor 1": {"Lower": 235.33, "Close": 238.81, "Upper": 242.3}, "Predictor 6": {"Lower": 233.88, "Close": 241.47, "Upper": 249.31}, "Predictor 3": {"Lower": 233.91, "Close": 237.29, "Upper": 240.68}, "Predictor 5": {"Lower": 233.8, "Close": 241.45, "Upper": 249.35}}}