{"INTC": {"Predictor 2": {"Upper": 45.79, "Close": 44.89, "Lower": 43.99}, "Predictor 5": {"Upper": 45.81, "Close": 44.44, "Lower": 43.12}, "Mean": {"Upper": 45.48, "Close": 44.21, "Lower": 42.97}, "Predictor 1": {"Upper": 44.77, "Close": 43.92, "Lower": 43.06}, "Predictor 3": {"Upper": 45.31, "Close": 44.54, "Lower": 43.77}, "Predictor 4": {"Upper": 45.6, "Close": 44.63, "Lower": 43.66}, "Predictor 6": {"Upper": 45.59, "Close": 42.82, "Lower": 40.22}}, "TSLA": {"Predictor 2": {"Upper": 325.51, "Close": 314.66, "Lower": 303.81}, "Predictor 5": {"Upper": 340.93, "Close": 320.6, "Lower": 301.47}, "Mean": {"Upper": 334.37, "Close": 320.27, "Lower": 306.62}, "Predictor 1": {"Upper": 340.15, "Close": 328.12, "Lower": 316.08}, "Predictor 3": {"Upper": 333.35, "Close": 323.77, "Lower": 314.2}, "Predictor 4": {"Upper": 332.8, "Close": 323.18, "Lower": 313.56}, "Predictor 6": {"Upper": 333.51, "Close": 311.33, "Lower": 290.62}}, "MSFT": {"Predictor 2": {"Upper": 87.21, "Close": 85.45, "Lower": 83.68}, "Predictor 5": {"Upper": 86.45, "Close": 83.95, "Lower": 81.51}, "Mean": {"Upper": 85.68, "Close": 83.85, "Lower": 82.04}, "Predictor 1": {"Upper": 85.53, "Close": 84.21, "Lower": 82.88}, "Predictor 3": {"Upper": 83.28, "Close": 81.85, "Lower": 80.43}, "Predictor 4": {"Upper": 85.4, "Close": 84.24, "Lower": 83.09}, "Predictor 6": {"Upper": 86.2, "Close": 83.39, "Lower": 80.68}}, "BA": {"Predictor 2": {"Upper": 262.89, "Close": 259.32, "Lower": 255.76}, "Predictor 5": {"Upper": 276.78, "Close": 249.92, "Lower": 225.67}, "Mean": {"Upper": 263.94, "Close": 255.65, "Lower": 247.85}, "Predictor 1": {"Upper": 260.39, "Close": 256.88, "Lower": 253.38}, "Predictor 3": {"Upper": 258.95, "Close": 255.23, "Lower": 251.51}, "Predictor 4": {"Upper": 259.29, "Close": 255.89, "Lower": 252.49}, "Predictor 6": {"Upper": 265.35, "Close": 256.68, "Lower": 248.29}}, "NVDA": {"Predictor 2": {"Upper": 202.72, "Close": 199.9, "Lower": 197.09}, "Predictor 5": {"Upper": 218.94, "Close": 206.92, "Lower": 195.56}, "Mean": {"Upper": 208.51, "Close": 202.63, "Lower": 196.95}, "Predictor 1": {"Upper": 202.28, "Close": 199.71, "Lower": 197.13}, "Predictor 3": {"Upper": 201.79, "Close": 197.67, "Lower": 193.56}, "Predictor 4": {"Upper": 210.55, "Close": 207.43, "Lower": 204.31}, "Predictor 6": {"Upper": 214.78, "Close": 204.15, "Lower": 194.05}}, "AAPL": {"Predictor 2": {"Upper": 167.6, "Close": 164.76, "Lower": 161.91}, "Predictor 5": {"Upper": 172.6, "Close": 167.11, "Lower": 161.8}, "Mean": {"Upper": 168.08, "Close": 164.25, "Lower": 160.48}, "Predictor 1": {"Upper": 167.23, "Close": 164.41, "Lower": 161.6}, "Predictor 3": {"Upper": 170.37, "Close": 167.31, "Lower": 164.25}, "Predictor 4": {"Upper": 159.36, "Close": 156.32, "Lower": 153.28}, "Predictor 6": {"Upper": 171.29, "Close": 165.58, "Lower": 160.07}}, "FB": {"Predictor 2": {"Upper": 179.93, "Close": 176.42, "Lower": 172.91}, "Predictor 5": {"Upper": 188.18, "Close": 179.94, "Lower": 172.07}, "Mean": {"Upper": 181.25, "Close": 175.65, "Lower": 170.16}, "Predictor 1": {"Upper": 183.85, "Close": 179.48, "Lower": 175.12}, "Predictor 3": {"Upper": 165.36, "Close": 159.05, "Lower": 152.74}, "Predictor 4": {"Upper": 181.96, "Close": 178.89, "Lower": 175.81}, "Predictor 6": {"Upper": 188.23, "Close": 180.11, "Lower": 172.34}}, "T": {"Predictor 2": {"Upper": 34.55, "Close": 33.81, "Lower": 33.08}, "Predictor 5": {"Upper": 34.3, "Close": 33.58, "Lower": 32.87}, "Mean": {"Upper": 34.28, "Close": 33.46, "Lower": 32.64}, "Predictor 1": {"Upper": 34.46, "Close": 33.74, "Lower": 33.01}, "Predictor 3": {"Upper": 34.44, "Close": 33.76, "Lower": 33.07}, "Predictor 4": {"Upper": 33.86, "Close": 33.19, "Lower": 32.53}, "Predictor 6": {"Upper": 34.08, "Close": 32.66, "Lower": 31.3}}, "AMZN": {"Predictor 2": {"Upper": 1102.62, "Close": 1083.36, "Lower": 1064.1}, "Predictor 5": {"Upper": 1153.19, "Close": 1106.18, "Lower": 1061.09}, "Mean": {"Upper": 1107.22, "Close": 1079.76, "Lower": 1052.93}, "Predictor 1": {"Upper": 1054.75, "Close": 1036.96, "Lower": 1019.16}, "Predictor 3": {"Upper": 1086.23, "Close": 1069.21, "Lower": 1052.2}, "Predictor 4": {"Upper": 1089.59, "Close": 1072.48, "Lower": 1055.36}, "Predictor 6": {"Upper": 1156.96, "Close": 1110.37, "Lower": 1065.66}}, "BAC": {"Predictor 2": {"Upper": 28.24, "Close": 27.56, "Lower": 26.88}, "Predictor 5": {"Upper": 29.28, "Close": 27.58, "Lower": 25.98}, "Mean": {"Upper": 28.21, "Close": 27.19, "Lower": 26.21}, "Predictor 1": {"Upper": 28.71, "Close": 28.05, "Lower": 27.38}, "Predictor 3": {"Upper": 25.53, "Close": 24.81, "Lower": 24.09}, "Predictor 4": {"Upper": 28.15, "Close": 27.54, "Lower": 26.94}, "Predictor 6": {"Upper": 29.33, "Close": 27.62, "Lower": 26.0}}}