{"BA": {"Predictor 3": {"Upper": 262.41, "Lower": 254.86, "Close": 258.63}, "Predictor 1": {"Upper": 264.07, "Lower": 256.93, "Close": 260.5}, "Predictor 5": {"Upper": 265.08, "Lower": 222.02, "Close": 242.6}, "Predictor 6": {"Upper": 269.67, "Lower": 253.12, "Close": 261.26}, "Mean": {"Upper": 264.82, "Lower": 250.08, "Close": 257.27}, "Predictor 4": {"Upper": 262.5, "Lower": 255.52, "Close": 259.01}, "Predictor 2": {"Upper": 265.19, "Lower": 258.05, "Close": 261.62}}, "BAC": {"Predictor 3": {"Upper": 26.41, "Lower": 25.18, "Close": 25.79}, "Predictor 1": {"Upper": 26.24, "Lower": 25.02, "Close": 25.63}, "Predictor 5": {"Upper": 27.72, "Lower": 24.38, "Close": 25.99}, "Predictor 6": {"Upper": 27.57, "Lower": 24.44, "Close": 25.96}, "Mean": {"Upper": 26.63, "Lower": 24.69, "Close": 25.65}, "Predictor 4": {"Upper": 25.09, "Lower": 23.82, "Close": 24.45}, "Predictor 2": {"Upper": 26.78, "Lower": 25.3, "Close": 26.04}}, "MSFT": {"Predictor 3": {"Upper": 77.46, "Lower": 75.15, "Close": 76.31}, "Predictor 1": {"Upper": 76.71, "Lower": 74.09, "Close": 75.4}, "Predictor 5": {"Upper": 78.71, "Lower": 74.22, "Close": 76.43}, "Predictor 6": {"Upper": 78.66, "Lower": 74.17, "Close": 76.39}, "Mean": {"Upper": 78.13, "Lower": 74.99, "Close": 76.55}, "Predictor 4": {"Upper": 77.91, "Lower": 75.69, "Close": 76.8}, "Predictor 2": {"Upper": 79.32, "Lower": 76.63, "Close": 77.98}}, "AAPL": {"Predictor 3": {"Upper": 161.01, "Lower": 155.37, "Close": 158.19}, "Predictor 1": {"Upper": 158.37, "Lower": 152.82, "Close": 155.59}, "Predictor 5": {"Upper": 160.89, "Lower": 148.59, "Close": 154.62}, "Predictor 6": {"Upper": 160.95, "Lower": 150.79, "Close": 155.79}, "Mean": {"Upper": 159.78, "Lower": 152.37, "Close": 156.04}, "Predictor 4": {"Upper": 158.62, "Lower": 153.46, "Close": 156.04}, "Predictor 2": {"Upper": 158.87, "Lower": 153.18, "Close": 156.02}}, "FB": {"Predictor 3": {"Upper": 178.33, "Lower": 170.64, "Close": 174.49}, "Predictor 1": {"Upper": 162.75, "Lower": 150.33, "Close": 156.54}, "Predictor 5": {"Upper": 179.81, "Lower": 164.55, "Close": 172.01}, "Predictor 6": {"Upper": 179.56, "Lower": 164.36, "Close": 171.79}, "Mean": {"Upper": 176.36, "Lower": 165.43, "Close": 170.84}, "Predictor 4": {"Upper": 176.98, "Lower": 170.48, "Close": 173.73}, "Predictor 2": {"Upper": 180.69, "Lower": 172.24, "Close": 176.46}}, "T": {"Predictor 3": {"Upper": 39.18, "Lower": 37.79, "Close": 38.48}, "Predictor 1": {"Upper": 39.24, "Lower": 37.91, "Close": 38.58}, "Predictor 5": {"Upper": 39.33, "Lower": 37.72, "Close": 38.52}, "Predictor 6": {"Upper": 40.48, "Lower": 36.82, "Close": 38.61}, "Mean": {"Upper": 39.45, "Lower": 37.64, "Close": 38.54}, "Predictor 4": {"Upper": 38.95, "Lower": 37.6, "Close": 38.27}, "Predictor 2": {"Upper": 39.54, "Lower": 37.98, "Close": 38.76}}, "NVDA": {"Predictor 3": {"Upper": 200.2, "Lower": 193.28, "Close": 196.74}, "Predictor 1": {"Upper": 191.39, "Lower": 186.01, "Close": 188.7}, "Predictor 5": {"Upper": 199.73, "Lower": 180.31, "Close": 189.77}, "Predictor 6": {"Upper": 201.18, "Lower": 178.18, "Close": 189.33}, "Mean": {"Upper": 196.18, "Lower": 185.16, "Close": 190.57}, "Predictor 4": {"Upper": 193.54, "Lower": 188.1, "Close": 190.82}, "Predictor 2": {"Upper": 191.04, "Lower": 185.09, "Close": 188.07}}, "INTC": {"Predictor 3": {"Upper": 37.78, "Lower": 36.15, "Close": 36.96}, "Predictor 1": {"Upper": 40.16, "Lower": 38.63, "Close": 39.39}, "Predictor 5": {"Upper": 40.88, "Lower": 38.5, "Close": 39.67}, "Predictor 6": {"Upper": 41.77, "Lower": 38.65, "Close": 40.18}, "Mean": {"Upper": 40.19, "Lower": 38.25, "Close": 39.21}, "Predictor 4": {"Upper": 40.1, "Lower": 38.63, "Close": 39.37}, "Predictor 2": {"Upper": 40.46, "Lower": 38.94, "Close": 39.7}}, "TSLA": {"Predictor 3": {"Upper": 364.02, "Lower": 343.1, "Close": 353.56}, "Predictor 1": {"Upper": 356.71, "Lower": 334.88, "Close": 345.79}, "Predictor 5": {"Upper": 378.83, "Lower": 334.89, "Close": 356.18}, "Predictor 6": {"Upper": 376.35, "Lower": 317.45, "Close": 345.65}, "Mean": {"Upper": 365.5, "Lower": 333.96, "Close": 349.41}, "Predictor 4": {"Upper": 361.2, "Lower": 342.38, "Close": 351.79}, "Predictor 2": {"Upper": 355.88, "Lower": 331.07, "Close": 343.48}}, "AMZN": {"Predictor 3": {"Upper": 1009.09, "Lower": 977.24, "Close": 993.16}, "Predictor 1": {"Upper": 1004.15, "Lower": 971.33, "Close": 987.74}, "Predictor 5": {"Upper": 1033.38, "Lower": 951.55, "Close": 991.62}, "Predictor 6": {"Upper": 1029.63, "Lower": 949.01, "Close": 988.5}, "Mean": {"Upper": 1017.06, "Lower": 967.24, "Close": 991.88}, "Predictor 4": {"Upper": 997.23, "Lower": 967.19, "Close": 982.21}, "Predictor 2": {"Upper": 1028.91, "Lower": 987.12, "Close": 1008.01}}}