{"AMZN": {"Predictor 3": {"Close": 1171.14, "Lower": 1153.39, "Upper": 1188.9}, "Mean": {"Close": 1174.11, "Lower": 1131.49, "Upper": 1219.47}, "Predictor 6": {"Close": 1177.66, "Lower": 1130.53, "Upper": 1226.76}, "Predictor 5": {"Close": 1219.37, "Lower": 1093.97, "Upper": 1359.14}, "Predictor 2": {"Close": 1175.74, "Lower": 1152.62, "Upper": 1198.85}, "Predictor 4": {"Close": 1160.12, "Lower": 1144.42, "Upper": 1175.81}, "Predictor 1": {"Close": 1140.66, "Lower": 1113.98, "Upper": 1167.33}}, "NVDA": {"Predictor 3": {"Close": 198.17, "Lower": 194.76, "Upper": 201.58}, "Mean": {"Close": 201.02, "Lower": 195.59, "Upper": 206.63}, "Predictor 6": {"Close": 200.99, "Lower": 191.06, "Upper": 211.44}, "Predictor 5": {"Close": 201.02, "Lower": 191.09, "Upper": 211.47}, "Predictor 2": {"Close": 199.74, "Lower": 196.24, "Upper": 203.24}, "Predictor 4": {"Close": 204.74, "Lower": 201.93, "Upper": 207.55}, "Predictor 1": {"Close": 201.49, "Lower": 198.48, "Upper": 204.5}}, "TSLA": {"Predictor 3": {"Close": 319.1, "Lower": 306.38, "Upper": 331.83}, "Mean": {"Close": 307.79, "Lower": 293.67, "Upper": 322.29}, "Predictor 6": {"Close": 309.14, "Lower": 290.74, "Upper": 328.71}, "Predictor 5": {"Close": 307.34, "Lower": 289.37, "Upper": 326.42}, "Predictor 2": {"Close": 297.87, "Lower": 281.44, "Upper": 314.29}, "Predictor 4": {"Close": 307.77, "Lower": 298.7, "Upper": 316.84}, "Predictor 1": {"Close": 305.52, "Lower": 295.39, "Upper": 315.65}}, "BA": {"Predictor 3": {"Close": 271.96, "Lower": 268.14, "Upper": 275.78}, "Mean": {"Close": 267.48, "Lower": 257.27, "Upper": 278.09}, "Predictor 6": {"Close": 289.66, "Lower": 272.22, "Upper": 308.22}, "Predictor 5": {"Close": 276.28, "Lower": 258.25, "Upper": 295.56}, "Predictor 2": {"Close": 216.45, "Lower": 201.45, "Upper": 231.45}, "Predictor 4": {"Close": 273.28, "Lower": 270.06, "Upper": 276.51}, "Predictor 1": {"Close": 277.25, "Lower": 273.47, "Upper": 281.02}}, "AAPL": {"Predictor 3": {"Close": 172.52, "Lower": 169.84, "Upper": 175.2}, "Mean": {"Close": 171.33, "Lower": 164.21, "Upper": 179.23}, "Predictor 6": {"Close": 166.92, "Lower": 141.82, "Upper": 196.46}, "Predictor 5": {"Close": 172.85, "Lower": 166.72, "Upper": 179.2}, "Predictor 2": {"Close": 172.42, "Lower": 169.43, "Upper": 175.4}, "Predictor 4": {"Close": 171.16, "Lower": 168.2, "Upper": 174.13}, "Predictor 1": {"Close": 172.14, "Lower": 169.26, "Upper": 175.02}}, "MSFT": {"Predictor 3": {"Close": 84.09, "Lower": 82.91, "Upper": 85.26}, "Mean": {"Close": 84.52, "Lower": 82.91, "Upper": 86.14}, "Predictor 6": {"Close": 84.37, "Lower": 81.92, "Upper": 86.89}, "Predictor 5": {"Close": 84.53, "Lower": 82.18, "Upper": 86.95}, "Predictor 2": {"Close": 84.39, "Lower": 83.17, "Upper": 85.6}, "Predictor 4": {"Close": 84.16, "Lower": 83.05, "Upper": 85.26}, "Predictor 1": {"Close": 85.56, "Lower": 84.23, "Upper": 86.89}}, "T": {"Predictor 3": {"Close": 36.83, "Lower": 36.13, "Upper": 37.53}, "Mean": {"Close": 36.6, "Lower": 35.8, "Upper": 37.42}, "Predictor 6": {"Close": 36.49, "Lower": 35.35, "Upper": 37.67}, "Predictor 5": {"Close": 36.36, "Lower": 35.59, "Upper": 37.14}, "Predictor 2": {"Close": 36.94, "Lower": 36.08, "Upper": 37.8}, "Predictor 4": {"Close": 36.66, "Lower": 35.99, "Upper": 37.32}, "Predictor 1": {"Close": 36.34, "Lower": 35.64, "Upper": 37.05}}, "BAC": {"Predictor 3": {"Close": 28.71, "Lower": 27.99, "Upper": 29.42}, "Mean": {"Close": 27.5, "Lower": 26.45, "Upper": 28.58}, "Predictor 6": {"Close": 28.19, "Lower": 26.55, "Upper": 29.93}, "Predictor 5": {"Close": 28.2, "Lower": 26.56, "Upper": 29.94}, "Predictor 2": {"Close": 25.51, "Lower": 24.67, "Upper": 26.36}, "Predictor 4": {"Close": 28.71, "Lower": 28.02, "Upper": 29.39}, "Predictor 1": {"Close": 25.69, "Lower": 24.94, "Upper": 26.44}}, "FB": {"Predictor 3": {"Close": 179.4, "Lower": 175.97, "Upper": 182.83}, "Mean": {"Close": 181.27, "Lower": 174.56, "Upper": 188.37}, "Predictor 6": {"Close": 192.46, "Lower": 173.86, "Upper": 213.04}, "Predictor 5": {"Close": 177.7, "Lower": 169.64, "Upper": 186.14}, "Predictor 2": {"Close": 179.97, "Lower": 176.52, "Upper": 183.42}, "Predictor 4": {"Close": 177.41, "Lower": 174.19, "Upper": 180.62}, "Predictor 1": {"Close": 180.68, "Lower": 177.19, "Upper": 184.17}}, "INTC": {"Predictor 3": {"Close": 40.92, "Lower": 39.63, "Upper": 42.2}, "Mean": {"Close": 44.28, "Lower": 42.77, "Upper": 45.85}, "Predictor 6": {"Close": 44.54, "Lower": 42.66, "Upper": 46.49}, "Predictor 5": {"Close": 45.93, "Lower": 42.67, "Upper": 49.43}, "Predictor 2": {"Close": 44.62, "Lower": 43.69, "Upper": 45.55}, "Predictor 4": {"Close": 44.69, "Lower": 43.94, "Upper": 45.44}, "Predictor 1": {"Close": 45.01, "Lower": 44.03, "Upper": 45.98}}}