{"TSLA": {"Predictor 2": {"Upper": 360.84, "Close": 350.13, "Lower": 339.42}, "Predictor 4": {"Upper": 362.77, "Close": 353.74, "Lower": 344.71}, "Predictor 1": {"Upper": 356.77, "Close": 347.24, "Lower": 337.72}, "Predictor 6": {"Upper": 386.04, "Close": 361.45, "Lower": 338.44}, "Predictor 3": {"Upper": 357.63, "Close": 347.9, "Lower": 338.16}, "Predictor 5": {"Upper": 404.3, "Close": 359.96, "Lower": 320.48}, "Mean": {"Upper": 371.39, "Close": 353.4, "Lower": 336.49}}, "BAC": {"Predictor 2": {"Upper": 26.27, "Close": 25.54, "Lower": 24.82}, "Predictor 4": {"Upper": 24.64, "Close": 23.92, "Lower": 23.21}, "Predictor 1": {"Upper": 25.28, "Close": 24.7, "Lower": 24.12}, "Predictor 6": {"Upper": 30.4, "Close": 26.36, "Lower": 22.86}, "Predictor 3": {"Upper": 25.64, "Close": 25.02, "Lower": 24.4}, "Predictor 5": {"Upper": 26.56, "Close": 24.99, "Lower": 23.51}, "Mean": {"Upper": 26.46, "Close": 25.09, "Lower": 23.82}}, "T": {"Predictor 2": {"Upper": 38.84, "Close": 38.16, "Lower": 37.47}, "Predictor 4": {"Upper": 39.2, "Close": 38.58, "Lower": 37.96}, "Predictor 1": {"Upper": 38.78, "Close": 38.09, "Lower": 37.39}, "Predictor 6": {"Upper": 39.82, "Close": 38.85, "Lower": 37.9}, "Predictor 3": {"Upper": 38.82, "Close": 38.15, "Lower": 37.47}, "Predictor 5": {"Upper": 40.19, "Close": 38.67, "Lower": 37.2}, "Mean": {"Upper": 39.28, "Close": 38.41, "Lower": 37.57}}, "FB": {"Predictor 2": {"Upper": 174.84, "Close": 171.2, "Lower": 167.57}, "Predictor 4": {"Upper": 173.69, "Close": 170.29, "Lower": 166.89}, "Predictor 1": {"Upper": 173.34, "Close": 169.66, "Lower": 165.98}, "Predictor 6": {"Upper": 176.81, "Close": 168.78, "Lower": 161.1}, "Predictor 3": {"Upper": 175.7, "Close": 171.73, "Lower": 167.76}, "Predictor 5": {"Upper": 183.23, "Close": 172.87, "Lower": 163.09}, "Mean": {"Upper": 176.27, "Close": 170.76, "Lower": 165.4}}, "BA": {"Predictor 2": {"Upper": 239.42, "Close": 235.35, "Lower": 231.28}, "Predictor 4": {"Upper": 238.87, "Close": 234.9, "Lower": 230.92}, "Predictor 1": {"Upper": 245.72, "Close": 241.92, "Lower": 238.12}, "Predictor 6": {"Upper": 245.62, "Close": 237.9, "Lower": 230.43}, "Predictor 3": {"Upper": 238.93, "Close": 235.2, "Lower": 231.46}, "Predictor 5": {"Upper": 245.63, "Close": 237.92, "Lower": 230.44}, "Mean": {"Upper": 242.36, "Close": 237.2, "Lower": 232.11}}, "INTC": {"Predictor 2": {"Upper": 37.04, "Close": 36.25, "Lower": 35.45}, "Predictor 4": {"Upper": 37.33, "Close": 36.51, "Lower": 35.7}, "Predictor 1": {"Upper": 37.2, "Close": 36.43, "Lower": 35.65}, "Predictor 6": {"Upper": 37.39, "Close": 36.28, "Lower": 35.2}, "Predictor 3": {"Upper": 36.87, "Close": 36.08, "Lower": 35.28}, "Predictor 5": {"Upper": 38.94, "Close": 36.49, "Lower": 34.19}, "Mean": {"Upper": 37.46, "Close": 36.34, "Lower": 35.24}}, "AMZN": {"Predictor 2": {"Upper": 1021.57, "Close": 1004.82, "Lower": 988.07}, "Predictor 4": {"Upper": 1005.56, "Close": 991.21, "Lower": 976.85}, "Predictor 1": {"Upper": 1015.42, "Close": 997.02, "Lower": 978.63}, "Predictor 6": {"Upper": 1025.47, "Close": 983.73, "Lower": 943.68}, "Predictor 3": {"Upper": 1009.29, "Close": 991.59, "Lower": 973.89}, "Predictor 5": {"Upper": 1062.42, "Close": 954.93, "Lower": 858.31}, "Mean": {"Upper": 1023.29, "Close": 987.22, "Lower": 953.24}}, "NVDA": {"Predictor 2": {"Upper": 171.43, "Close": 168.49, "Lower": 165.56}, "Predictor 4": {"Upper": 174.71, "Close": 171.76, "Lower": 168.82}, "Predictor 1": {"Upper": 168.47, "Close": 166.15, "Lower": 163.83}, "Predictor 6": {"Upper": 171.8, "Close": 155.72, "Lower": 141.15}, "Predictor 3": {"Upper": 174.04, "Close": 171.22, "Lower": 168.41}, "Predictor 5": {"Upper": 177.63, "Close": 166.86, "Lower": 156.74}, "Mean": {"Upper": 173.01, "Close": 166.7, "Lower": 160.75}}, "AAPL": {"Predictor 2": {"Upper": 157.25, "Close": 154.44, "Lower": 151.63}, "Predictor 4": {"Upper": 163.25, "Close": 159.86, "Lower": 156.46}, "Predictor 1": {"Upper": 161.51, "Close": 158.51, "Lower": 155.51}, "Predictor 6": {"Upper": 161.78, "Close": 156.59, "Lower": 151.58}, "Predictor 3": {"Upper": 159.43, "Close": 156.47, "Lower": 153.52}, "Predictor 5": {"Upper": 159.8, "Close": 154.41, "Lower": 149.2}, "Mean": {"Upper": 160.5, "Close": 156.71, "Lower": 152.98}}, "MSFT": {"Predictor 2": {"Upper": 73.58, "Close": 72.36, "Lower": 71.15}, "Predictor 4": {"Upper": 70.45, "Close": 69.03, "Lower": 67.62}, "Predictor 1": {"Upper": 73.84, "Close": 72.65, "Lower": 71.45}, "Predictor 6": {"Upper": 90.74, "Close": 78.45, "Lower": 67.82}, "Predictor 3": {"Upper": 73.31, "Close": 72.16, "Lower": 71.0}, "Predictor 5": {"Upper": 74.94, "Close": 72.72, "Lower": 70.56}, "Mean": {"Upper": 76.14, "Close": 72.89, "Lower": 69.93}}}